pkg/__init__.py
cnuv-0.1.dist-info/METADATA
cnuv-0.1.dist-info/WHEEL
cnuv-0.1.dist-info/top_level.txt
cnuv-0.1.dist-info/RECORD
