Metadata-Version: 2.1
Name: cnuv
Version: 0.1
Summary: This is the package with all the cn codes
Author: Yuvraj
